src/alu.v
module alu (
    output reg [31:0] result,
    input      signed [31:0] src_a,
    input      signed [31:0] src_b,
    input             aresetn,  // currently unused
    input       [3:0] instr
);

    always @(*) begin
        case (instr)
            4'b0000: result = src_a + src_b;                                  // ADD
            4'b0001: result = src_a - src_b;                                  // SUB
            4'b0010: result = src_a & src_b;                                  // AND
            4'b0011: result = src_a | src_b;                                  // OR
            4'b0100: result = src_a ^ src_b;                                  // XOR
            4'b0101: result = src_a << src_b;                                 // SHL
            4'b0110: result = src_a >>> src_b;                                // Arithmetic right shift
            4'b0111: result = (src_a < src_b) ? 1 : 0;                        // SLT (signed)
            4'b1000: result = (src_a == src_b) ? 1 : 0;                       // EQ
            4'b1001: result = (src_a != src_b) ? 1 : 0;                       // NEQ
            4'b1010: result = (src_a >= src_b) ? 1 : 0;                       // GTE (signed)
            4'b1011: result = ($unsigned(src_a) < $unsigned(src_b)) ? 1 : 0;  // LTU
            4'b1100: result = ($unsigned(src_a) >= $unsigned(src_b)) ? 1 : 0; // GTU
            4'b1101: result = src_a * src_b;                                  // MUL
            4'b1110: result = src_a / src_b;                                  // DIV
            4'b1111: result = src_a % src_b;                                  // MOD
            default: result = 0;
        endcase
    end

endmodule

tb/unit/alu_tb.v
`timescale 1ns / 1ps

module alu_tb;

  // Inputs
  reg [31:0] src_a;
  reg [31:0] src_b;
  reg [3:0]  instr;
  reg        aresetn;

  // Output
  wire [31:0] result;

  // Instantiate the ALU
  alu dut (
    .result(result),
    .src_a(src_a),
    .src_b(src_b),
    .aresetn(aresetn),
    .instr(instr)
  );

  initial begin
    $dumpfile("dump.vcd");
    $dumpvars(0, alu_tb);

    aresetn = 1;         // Not used yet but wired
    src_a = 32'd10;
    src_b = 32'd3;

    // ADD
    instr = 4'b0000; #10;
    // SUB
    instr = 4'b0001; #10;
    // AND
    instr = 4'b0010; #10;
    // OR
    instr = 4'b0011; #10;
    // XOR
    instr = 4'b0100; #10;
    // SHL
    instr = 4'b0101; #10;
    // SHR
    instr = 4'b0110; #10;
    // SLT (signed)
    instr = 4'b0111; #10;
    // EQ
    instr = 4'b1000; #10;
    // NEQ
    instr = 4'b1001; #10;
    // GTE (signed)
    instr = 4'b1010; #10;
    // LTU (unsigned)
    instr = 4'b1011; #10;
    // GTU (unsigned)
    instr = 4'b1100; #10;
    // MUL
    instr = 4'b1101; #10;
    // DIV
    instr = 4'b1110; #10;
    // MOD
    instr = 4'b1111; #10;

    $finish;
  end

endmodule

sim/dump.vcd
$date
	Thu Jul 10 09:38:08 2025
$end
$version
	Icarus Verilog
$end
$timescale
	1ps
$end
$scope module alu_tb $end
$var wire 32 ! result [31:0] $end
$var reg 1 " aresetn $end
$var reg 4 # instr [3:0] $end
$var reg 32 $ src_a [31:0] $end
$var reg 32 % src_b [31:0] $end
$scope module dut $end
$var wire 1 " aresetn $end
$var wire 4 & instr [3:0] $end
$var wire 32 ' src_a [31:0] $end
$var wire 32 ( src_b [31:0] $end
$var reg 32 ) result [31:0] $end
$upscope $end
$upscope $end
$enddefinitions $end
$comment Show the parameter values. $end
$dumpall
$end
#0
$dumpvars
b1101 )
b11 (
b1010 '
b0 &
b11 %
b1010 $
b0 #
1"
b1101 !
$end
#10000
b111 !
b111 )
b1 #
b1 &
#20000
b10 !
b10 )
b10 #
b10 &
#30000
b1011 !
b1011 )
b11 #
b11 &
#40000
b1001 !
b1001 )
b100 #
b100 &
#50000
b1010000 !
b1010000 )
b101 #
b101 &
#60000
b1 !
b1 )
b110 #
b110 &
#70000
b0 !
b0 )
b111 #
b111 &
#80000
b1000 #
b1000 &
#90000
b1 !
b1 )
b1001 #
b1001 &
#100000
b1010 #
b1010 &
#110000
b0 !
b0 )
b1011 #
b1011 &
#120000
b1 !
b1 )
b1100 #
b1100 &
#130000
b11110 !
b11110 )
b1101 #
b1101 &
#140000
b11 !
b11 )
b1110 #
b1110 &
#150000
b1 !
b1 )
b1111 #
b1111 &
